[
  {
    "id": "dc5e8066-960b-461c-919e-4a98368158c4",
    "name": "16 Anni e Incinta",
    "region": "it",
    "category": "Pluto TV",
    "logo": "",
    "streamUrl": "https://jmp2.uk/plu-60940a07d88ba90007b9cb71.m3u8"
  },
  {
    "id": "85f93305-bdf8-4ebf-b56b-88feba0d4fe6",
    "name": "Affare Fatto",
    "region": "it",
    "category": "Pluto TV",
    "logo": "",
    "streamUrl": "https://jmp2.uk/plu-64ec5c6644fe100009d114ae.m3u8"
  },
  {
    "id": "f60900de-b75c-43e5-9d98-db7f43b7bd4a",
    "name": "Alice Nevers",
    "region": "it",
    "category": "Pluto TV",
    "logo": "",
    "streamUrl": "https://jmp2.uk/plu-66d9aa4315d2c60008d4ac40.m3u8"
  },
  {
    "id": "5a053b57-3b0b-4ced-b1e6-27c64a543b9c",
    "name": "Andromeda",
    "region": "it",
    "category": "Pluto TV",
    "logo": "",
    "streamUrl": "https://jmp2.uk/plu-60802d37ee238e0007c94e64.m3u8"
  },
  {
    "id": "c6a8cc93-f54b-4e24-85a3-15a42f973a6e",
    "name": "Autostop per il cielo",
    "region": "it",
    "category": "Pluto TV",
    "logo": "",
    "streamUrl": "https://jmp2.uk/plu-638f286445264d00084ec6dc.m3u8"
  },
  {
    "id": "626ccfe1-7a80-4c25-a340-955ad6e933c5",
    "name": "Barbie & Friends",
    "region": "it",
    "category": "Pluto TV",
    "logo": "",
    "streamUrl": "https://jmp2.uk/plu-686cfdf894a028da3aac4252.m3u8"
  },
  {
    "id": "d750a6c4-c167-46c7-9774-8a9f98752d52",
    "name": "BBC Series",
    "region": "it",
    "category": "Pluto TV",
    "logo": "",
    "streamUrl": "https://jmp2.uk/plu-62e7fa5ab5062e0007dcf97d.m3u8"
  },
  {
    "id": "c4ad9d4a-2b79-431e-a525-98dd157ddef7",
    "name": "Carabinieri",
    "region": "it",
    "category": "Pluto TV",
    "logo": "",
    "streamUrl": "https://jmp2.uk/plu-66a0eea88561260008b1c5d0.m3u8"
  },
  {
    "id": "0d7c5605-c409-4aec-9af3-de2f0a129ecd",
    "name": "Catfish",
    "region": "it",
    "category": "Pluto TV",
    "logo": "",
    "streamUrl": "https://jmp2.uk/plu-6093f9ed2c75660007322bb7.m3u8"
  },
  {
    "id": "aefc88e9-c574-41b0-ae7b-e3f90620f040",
    "name": "CBS News 24/7 (720p)",
    "region": "it",
    "category": "Pluto TV",
    "logo": "",
    "streamUrl": "https://jmp2.uk/plu-6231ec4b62cd1f0007093c7b.m3u8"
  },
  {
    "id": "a12295e0-48b0-4bc7-9ecf-01bbd36bf2e2",
    "name": "Cherif",
    "region": "it",
    "category": "Pluto TV",
    "logo": "",
    "streamUrl": "https://jmp2.uk/plu-66a8c7aefe11e500085b1587.m3u8"
  },
  {
    "id": "cd6438ce-dc45-49d9-a4cb-0c6f2a7e6b4b",
    "name": "Cin Cin",
    "region": "it",
    "category": "Pluto TV",
    "logo": "",
    "streamUrl": "https://jmp2.uk/plu-65cb78b83a116800079e2e35.m3u8"
  },
  {
    "id": "9ba86cca-7bbf-4795-9de9-ff2510c004b4",
    "name": "Cinema Poliziottesco",
    "region": "it",
    "category": "Pluto TV",
    "logo": "",
    "streamUrl": "https://jmp2.uk/plu-671754d8e482950008962aaf.m3u8"
  },
  {
    "id": "e34231c8-bb4c-44bd-816a-df9bac2f1bda",
    "name": "CineThriller (720p)",
    "region": "it",
    "category": "Pluto TV",
    "logo": "",
    "streamUrl": "https://jmp2.uk/plu-653660b4295b840008a70ba3.m3u8"
  },
  {
    "id": "9c9cbec8-7b05-4994-9349-f93b6131c3d4",
    "name": "Duri a Morire (720p)",
    "region": "it",
    "category": "Pluto TV",
    "logo": "",
    "streamUrl": "https://jmp2.uk/plu-65f865a62873090008d06382.m3u8"
  },
  {
    "id": "7f2e9905-a9e0-4bd4-8776-121256a7a16a",
    "name": "Dynasty",
    "region": "it",
    "category": "Pluto TV",
    "logo": "",
    "streamUrl": "https://jmp2.uk/plu-65cb76ea11ced70008206b66.m3u8"
  },
  {
    "id": "cf808a3b-ed91-4101-a8e3-f31a2428558b",
    "name": "Euronews",
    "region": "it",
    "category": "Pluto TV",
    "logo": "",
    "streamUrl": "https://jmp2.uk/plu-61b86ea479a4390007c6d5fc.m3u8"
  },
  {
    "id": "2820bd36-a692-479d-9243-45f8a9830847",
    "name": "Extreme Makeover Home Edition",
    "region": "it",
    "category": "Pluto TV",
    "logo": "",
    "streamUrl": "https://jmp2.uk/plu-6661739641af6400080cd8f1.m3u8"
  },
  {
    "id": "79ebbd3e-8406-42e6-a8f2-ca6ffe80f519",
    "name": "FailArmy (720p)",
    "region": "it",
    "category": "Pluto TV",
    "logo": "",
    "streamUrl": "https://jmp2.uk/plu-608014d19a26320007c92ab6.m3u8"
  },
  {
    "id": "aac22517-b76b-40d0-9f3c-6319079fd5bd",
    "name": "FIFA+ (720p)",
    "region": "it",
    "category": "Pluto TV",
    "logo": "",
    "streamUrl": "https://jmp2.uk/plu-660bfc4424e1d000085b5f93.m3u8"
  },
  {
    "id": "ed556f76-1b98-4389-a605-8c9b9222ea36",
    "name": "Flashpoint",
    "region": "it",
    "category": "Pluto TV",
    "logo": "",
    "streamUrl": "https://jmp2.uk/plu-66d7120815d2c60008cec006.m3u8"
  },
  {
    "id": "5c64c3ce-2f20-484f-871c-17e6571657d9",
    "name": "Forensic Files",
    "region": "it",
    "category": "Pluto TV",
    "logo": "",
    "streamUrl": "https://jmp2.uk/plu-64ec5cf50f73a800081310a5.m3u8"
  },
  {
    "id": "42e74c10-e265-4d26-8032-e4bcf2fe8a2b",
    "name": "Geordie Shore",
    "region": "it",
    "category": "Pluto TV",
    "logo": "",
    "streamUrl": "https://jmp2.uk/plu-619263ee9541940007d20d60.m3u8"
  },
  {
    "id": "6cc71f4e-a326-42cc-8582-118720b43e07",
    "name": "Gli Immortali | Van Damme vs Lundgren (720p)",
    "region": "it",
    "category": "Pluto TV",
    "logo": "",
    "streamUrl": "https://jmp2.uk/plu-6536608b4f123d000876b78b.m3u8"
  },
  {
    "id": "b1626f54-88ba-4bc7-ab06-5ec4bea36ed6",
    "name": "Gormiti",
    "region": "it",
    "category": "Pluto TV",
    "logo": "",
    "streamUrl": "https://jmp2.uk/plu-66a8c64814a2bb00084d09d6.m3u8"
  },
  {
    "id": "19c1d5a0-a89f-4b7e-9558-3e21ab09d105",
    "name": "Hell's Kitchen (720p)",
    "region": "it",
    "category": "Pluto TV",
    "logo": "",
    "streamUrl": "https://jmp2.uk/plu-664f0ddbf78a8500092dcffa.m3u8"
  },
  {
    "id": "3f86dac8-f0e8-4714-874c-234107759b99",
    "name": "Horror Club",
    "region": "it",
    "category": "Pluto TV",
    "logo": "",
    "streamUrl": "https://jmp2.uk/plu-66c35c0c92b1af0008c8e83a.m3u8"
  },
  {
    "id": "a322b177-cce0-49f0-add9-492a9c62ffdf",
    "name": "I Puffi",
    "region": "it",
    "category": "Pluto TV",
    "logo": "",
    "streamUrl": "https://jmp2.uk/plu-68adb5853efb41cd97ce413d.m3u8"
  },
  {
    "id": "1a3db41b-bc1d-45fb-96a7-ea41075857d4",
    "name": "I soliti idioti",
    "region": "it",
    "category": "Pluto TV",
    "logo": "",
    "streamUrl": "https://jmp2.uk/plu-6602acadb2abe500081cf28a.m3u8"
  },
  {
    "id": "070ad8ee-5dcf-4d60-81df-df0b64fba269",
    "name": "Il Banco dei Pugni",
    "region": "it",
    "category": "Pluto TV",
    "logo": "",
    "streamUrl": "https://jmp2.uk/plu-60e4507a06171800072339a3.m3u8"
  },
  {
    "id": "65d2d6fc-91a4-49f1-9b07-d23fa8a0a352",
    "name": "Il Testimone",
    "region": "it",
    "category": "Pluto TV",
    "logo": "",
    "streamUrl": "https://jmp2.uk/plu-61fbd3f0733df400076c9a2d.m3u8"
  },
  {
    "id": "c4a270d7-ba02-413d-9b88-55f095f9088f",
    "name": "Inazuma Eleven",
    "region": "it",
    "category": "Pluto TV",
    "logo": "",
    "streamUrl": "https://jmp2.uk/plu-612375086abc84000738fc03.m3u8"
  },
  {
    "id": "49d111d4-9bf0-4f20-9eae-818c33b3e904",
    "name": "Just for Laughs GAGS (720p)",
    "region": "it",
    "category": "Pluto TV",
    "logo": "",
    "streamUrl": "https://jmp2.uk/plu-6093f48c95132a00075fd859.m3u8"
  },
  {
    "id": "604826c2-a40a-4d44-b248-d3dd6f068170",
    "name": "Le sorelle McLeod",
    "region": "it",
    "category": "Pluto TV",
    "logo": "",
    "streamUrl": "https://jmp2.uk/plu-60a2837f8154ab0007c4dcdf.m3u8"
  },
  {
    "id": "e7d61309-2085-4fae-9542-8ef2a31573ed",
    "name": "LOL Just For Laughs (720p)",
    "region": "it",
    "category": "Pluto TV",
    "logo": "",
    "streamUrl": "https://jmp2.uk/plu-65d7211d0d45610008ffcf92.m3u8"
  },
  {
    "id": "d74e1d66-227b-4fc3-a523-ddb454c823ed",
    "name": "Love Boat",
    "region": "it",
    "category": "Pluto TV",
    "logo": "",
    "streamUrl": "https://jmp2.uk/plu-65cb76723a116800079e1fc3.m3u8"
  },
  {
    "id": "88c3fbf6-0da6-490d-a5ac-011824b6c90e",
    "name": "Mai dire sì",
    "region": "it",
    "category": "Pluto TV",
    "logo": "",
    "streamUrl": "https://jmp2.uk/plu-6349279ed5023700078f2bc2.m3u8"
  },
  {
    "id": "13830fd5-f0b2-4b48-8d76-46a4021a49ae",
    "name": "Mattel Junior",
    "region": "it",
    "category": "Pluto TV",
    "logo": "",
    "streamUrl": "https://jmp2.uk/plu-686cfe983ffa5e0c91cdb5df.m3u8"
  },
  {
    "id": "7407e657-d3c7-40c7-8fe8-33d298c897de",
    "name": "Mayday: Disastro Aereo (720p)",
    "region": "it",
    "category": "Pluto TV",
    "logo": "",
    "streamUrl": "https://jmp2.uk/plu-690cb9140d121b44ad925ac9.m3u8"
  },
  {
    "id": "9e6672a1-9f96-4755-9acb-335f2966b39b",
    "name": "Mission Impossible",
    "region": "it",
    "category": "Pluto TV",
    "logo": "",
    "streamUrl": "https://jmp2.uk/plu-65cb77853ba51e00084cba02.m3u8"
  },
  {
    "id": "f3f5d91e-e1be-43ba-a5cb-becec44aceac",
    "name": "MODUS Super Series Darts",
    "region": "it",
    "category": "Pluto TV",
    "logo": "",
    "streamUrl": "https://jmp2.uk/plu-671655b2daad7f00085d202d.m3u8"
  },
  {
    "id": "6cb18024-cf13-4a7c-b645-e74077bcf9d5",
    "name": "Naturescape (720p)",
    "region": "it",
    "category": "Pluto TV",
    "logo": "",
    "streamUrl": "https://jmp2.uk/plu-610a9ebe8c2ac2000734776e.m3u8"
  },
  {
    "id": "d429b960-e276-49d9-9526-e6b42a17901b",
    "name": "Pluto TV Alberto Sordi",
    "region": "it",
    "category": "Pluto TV",
    "logo": "",
    "streamUrl": "https://jmp2.uk/plu-661f8f01801af800083d9d81.m3u8"
  },
  {
    "id": "74cf27e6-9aad-4d18-87ee-127ba07bc205",
    "name": "Pluto TV Anime",
    "region": "it",
    "category": "Pluto TV",
    "logo": "",
    "streamUrl": "https://jmp2.uk/plu-65b90daed77d450008a43345.m3u8"
  },
  {
    "id": "cedd75df-cb94-47ae-9b3a-7b5060876b90",
    "name": "Pluto TV Christmas tutto l'anno",
    "region": "it",
    "category": "Pluto TV",
    "logo": "",
    "streamUrl": "https://jmp2.uk/plu-612e05b885183d0007958101.m3u8"
  },
  {
    "id": "2bde449d-ff34-40c9-bad4-70724d8aed91",
    "name": "Pluto TV Cinema Italiano",
    "region": "it",
    "category": "Pluto TV",
    "logo": "",
    "streamUrl": "https://jmp2.uk/plu-608aa7d8359b270007861489.m3u8"
  },
  {
    "id": "e680a806-31be-4327-8165-ab697a421683",
    "name": "Pluto TV Cinema Orientale",
    "region": "it",
    "category": "Pluto TV",
    "logo": "",
    "streamUrl": "https://jmp2.uk/plu-6786235bd648bf0008c2780a.m3u8"
  },
  {
    "id": "b985f36f-cd8b-4a81-b1c6-0ae96dc0e46f",
    "name": "Pluto TV Cucina",
    "region": "it",
    "category": "Pluto TV",
    "logo": "",
    "streamUrl": "https://jmp2.uk/plu-608aa718a8ec810007d87fee.m3u8"
  },
  {
    "id": "1ed981a4-d85d-4172-9f49-771dc212422a",
    "name": "Pluto TV Dive Italiane",
    "region": "it",
    "category": "Pluto TV",
    "logo": "",
    "streamUrl": "https://jmp2.uk/plu-6875080e3484d607323641f8.m3u8"
  },
  {
    "id": "6f26c957-cb8e-49dc-994a-d460023bcbeb",
    "name": "Pluto TV Documentari",
    "region": "it",
    "category": "Pluto TV",
    "logo": "",
    "streamUrl": "https://jmp2.uk/plu-608aa8a5709d6b0007b132fe.m3u8"
  },
  {
    "id": "282e27f4-1b0b-4415-b423-caaf3f9dc34a",
    "name": "Pluto TV Eros",
    "region": "it",
    "category": "Pluto TV",
    "logo": "",
    "streamUrl": "https://jmp2.uk/plu-66335489307fa300082bd6e4.m3u8"
  },
  {
    "id": "e33f67f8-09b6-48e0-9ee8-b5a2644cc9a8",
    "name": "Pluto TV Film",
    "region": "it",
    "category": "Pluto TV",
    "logo": "",
    "streamUrl": "https://jmp2.uk/plu-608aa17fb9f4490007e6419a.m3u8"
  },
  {
    "id": "7bba9b9d-a764-4f65-8411-322f969eeee8",
    "name": "Pluto TV Film Azione",
    "region": "it",
    "category": "Pluto TV",
    "logo": "",
    "streamUrl": "https://jmp2.uk/plu-608aa20a2e7f270007c4878d.m3u8"
  },
  {
    "id": "1b338065-1d89-4cc8-8f1b-3dba6aac3a99",
    "name": "Pluto TV Film Azione+",
    "region": "it",
    "category": "Pluto TV",
    "logo": "",
    "streamUrl": "https://jmp2.uk/stvp-ITBC3000003CT?.m3u8"
  },
  {
    "id": "9a61cbbf-7c73-4109-9bbb-8c4a0f482342",
    "name": "Pluto TV Film Commedia",
    "region": "it",
    "category": "Pluto TV",
    "logo": "",
    "streamUrl": "https://jmp2.uk/plu-608aa512d67fd900072323db.m3u8"
  },
  {
    "id": "2f82a642-dfd1-4a68-b1f0-a98b7912be6e",
    "name": "Pluto TV Film Commedia+",
    "region": "it",
    "category": "Pluto TV",
    "logo": "",
    "streamUrl": "https://jmp2.uk/stvp-ITBC3000002WL?.m3u8"
  },
  {
    "id": "c2706acc-32a2-4f11-9d11-6571eedef7ff",
    "name": "Pluto TV Film Romantici",
    "region": "it",
    "category": "Pluto TV",
    "logo": "",
    "streamUrl": "https://jmp2.uk/plu-608aa4a4cc92820007b663af.m3u8"
  },
  {
    "id": "16e16bda-d552-47fa-a318-8f068adeff86",
    "name": "Pluto TV Film Romantici+",
    "region": "it",
    "category": "Pluto TV",
    "logo": "",
    "streamUrl": "https://jmp2.uk/stvp-ITAJ3800009J1?.m3u8"
  },
  {
    "id": "cdb37880-9fcc-40c6-a3cb-c6d903c21f04",
    "name": "Pluto TV Film Storici",
    "region": "it",
    "category": "Pluto TV",
    "logo": "",
    "streamUrl": "https://jmp2.uk/plu-68750875759366af05a151ce.m3u8"
  },
  {
    "id": "b236eaf1-3406-4a07-8d80-eb4e0ef29861",
    "name": "Pluto TV Film Thriller",
    "region": "it",
    "category": "Pluto TV",
    "logo": "",
    "streamUrl": "https://jmp2.uk/plu-608aa5e995132a00075f7005.m3u8"
  },
  {
    "id": "8f485655-6cc2-4da6-866b-d6fd1b1b7f33",
    "name": "Pluto TV Film+",
    "region": "it",
    "category": "Pluto TV",
    "logo": "",
    "streamUrl": "https://jmp2.uk/stvp-ITAJ38000055E?.m3u8"
  },
  {
    "id": "PlutoTVHorror.us@IT",
    "name": "Pluto TV Horror",
    "region": "it",
    "category": "Pluto TV",
    "logo": "",
    "streamUrl": "https://jmp2.uk/plu-61c09e3ac210ed0007606620.m3u8"
  },
  {
    "id": "fa886206-e6cb-4ee8-b679-4496e5093041",
    "name": "Pluto TV Legami Letali",
    "region": "it",
    "category": "Pluto TV",
    "logo": "",
    "streamUrl": "https://jmp2.uk/plu-64808a8c536e0c0008a276d1.m3u8"
  },
  {
    "id": "b87a0c33-fdce-4584-bb1d-45906d077b64",
    "name": "Pluto TV Natura",
    "region": "it",
    "category": "Pluto TV",
    "logo": "",
    "streamUrl": "https://jmp2.uk/plu-60802b37709d6b0007b0c549.m3u8"
  },
  {
    "id": "ae91e43a-c2c9-45ef-9f1d-d2dd69265379",
    "name": "Pluto TV Notti di Crimine",
    "region": "it",
    "category": "Pluto TV",
    "logo": "",
    "streamUrl": "https://jmp2.uk/plu-6911c9b88caba6f046c5ca8f.m3u8"
  },
  {
    "id": "befd6182-1719-4203-ac91-6e750eab490e",
    "name": "Pluto TV Notti di Passione",
    "region": "it",
    "category": "Pluto TV",
    "logo": "",
    "streamUrl": "https://jmp2.uk/plu-6911c9704316999535eb21cf.m3u8"
  },
  {
    "id": "c56cf6c3-acd2-44ff-b855-9091862bad3b",
    "name": "Pluto TV Notti di Sangue",
    "region": "it",
    "category": "Pluto TV",
    "logo": "",
    "streamUrl": "https://jmp2.uk/plu-6911c92b4316999535eb1e08.m3u8"
  },
  {
    "id": "0997f349-fee2-4043-a4c4-73a90b0a1097",
    "name": "Pluto TV Notti di Terrore",
    "region": "it",
    "category": "Pluto TV",
    "logo": "",
    "streamUrl": "https://jmp2.uk/plu-6911c8dd8caba6f046c5c5d5.m3u8"
  },
  {
    "id": "408c3cd1-bfe7-4c1a-8f3d-908f6da8eb29",
    "name": "Pluto TV Paranormal",
    "region": "it",
    "category": "Pluto TV",
    "logo": "",
    "streamUrl": "https://jmp2.uk/plu-66c70033b1a34600087bb09a.m3u8"
  },
  {
    "id": "b125cb95-9322-4438-a083-6915128242a4",
    "name": "Pluto TV Real Life",
    "region": "it",
    "category": "Pluto TV",
    "logo": "",
    "streamUrl": "https://jmp2.uk/plu-60801976f92a750007a0699c.m3u8"
  },
  {
    "id": "6e824f4f-c236-4e9d-bef6-26c1bf127a7d",
    "name": "Pluto TV Real Life+",
    "region": "it",
    "category": "Pluto TV",
    "logo": "",
    "streamUrl": "https://jmp2.uk/stvp-ITAJ3800006UB?.m3u8"
  },
  {
    "id": "8fe6b50c-d822-44e1-924a-ed8cb48f8eba",
    "name": "Pluto TV Scherzi e risate",
    "region": "it",
    "category": "Pluto TV",
    "logo": "",
    "streamUrl": "https://jmp2.uk/plu-609404b0a8ec810007d8de9d.m3u8"
  },
  {
    "id": "70b9b795-583f-46e8-ad4f-32ba63c7f40a",
    "name": "Pluto TV Sci-Fi",
    "region": "it",
    "category": "Pluto TV",
    "logo": "",
    "streamUrl": "https://jmp2.uk/plu-61728bb9ee3773000840c1fa.m3u8"
  },
  {
    "id": "0222f584-4ba8-4846-9fb7-8e79d08bdd79",
    "name": "Pluto TV Serie",
    "region": "it",
    "category": "Pluto TV",
    "logo": "",
    "streamUrl": "https://jmp2.uk/plu-60b9ff2722bfa400072676ef.m3u8"
  },
  {
    "id": "ce11635b-41b8-43e6-96a5-91a477b6ee8d",
    "name": "Pluto TV Serie Crime",
    "region": "it",
    "category": "Pluto TV",
    "logo": "",
    "streamUrl": "https://jmp2.uk/plu-608aa777b907770007e5d05d.m3u8"
  },
  {
    "id": "aba3d0a0-6ef1-4664-b0d5-734ac7833130",
    "name": "Pluto TV Serie Sci-Fi",
    "region": "it",
    "category": "Pluto TV",
    "logo": "",
    "streamUrl": "https://jmp2.uk/plu-67ed14aaf7c5d70b9089c3bf.m3u8"
  },
  {
    "id": "9938a869-5f80-4397-a4ec-a8e276326414",
    "name": "Pluto TV Serie+",
    "region": "it",
    "category": "Pluto TV",
    "logo": "",
    "streamUrl": "https://jmp2.uk/stvp-ITAJ3800007P8?.m3u8"
  },
  {
    "id": "e1dc2527-9312-4666-bd1a-917819dbbd8d",
    "name": "Pluto TV Shore",
    "region": "it",
    "category": "Pluto TV",
    "logo": "",
    "streamUrl": "https://jmp2.uk/plu-67e3b0d2443f0671bc8a1297.m3u8"
  },
  {
    "id": "96ae2262-2b97-4c72-98dc-57b13e127186",
    "name": "Pluto TV Snooker 900 (720p)",
    "region": "it",
    "category": "Pluto TV",
    "logo": "",
    "streamUrl": "https://jmp2.uk/plu-69148c76e9dec35c9269a16c.m3u8"
  },
  {
    "id": "54a4b4c9-6ce1-4699-b3a3-1e6b837cd471",
    "name": "Pluto TV Sport",
    "region": "it",
    "category": "Pluto TV",
    "logo": "",
    "streamUrl": "https://jmp2.uk/plu-608030eff4b6f70007e1684c.m3u8"
  },
  {
    "id": "baed6e4b-5327-407f-8b18-583176ff6271",
    "name": "Pluto TV Storia",
    "region": "it",
    "category": "Pluto TV",
    "logo": "",
    "streamUrl": "https://jmp2.uk/plu-65253fdf3fd33c00080214a3.m3u8"
  },
  {
    "id": "d09c7102-3832-42c4-beea-4bcceca86e53",
    "name": "Pluto TV Teen (720p)",
    "region": "it",
    "category": "Pluto TV",
    "logo": "",
    "streamUrl": "https://jmp2.uk/plu-63eb573ba99571000897135b.m3u8"
  },
  {
    "id": "5e6d6ba4-9bb1-4487-9a37-0631e7ed3dc0",
    "name": "Pluto TV Totò",
    "region": "it",
    "category": "Pluto TV",
    "logo": "",
    "streamUrl": "https://jmp2.uk/plu-65253f9881f942000833ccd5.m3u8"
  },
  {
    "id": "fd1f4fd2-1cfc-4277-a27d-0b8db11fa4b5",
    "name": "Pluto TV True Crime",
    "region": "it",
    "category": "Pluto TV",
    "logo": "",
    "streamUrl": "https://jmp2.uk/plu-66d9ab4bf0f17500084e9b7e.m3u8"
  },
  {
    "id": "6c3e2324-6eb1-4676-8537-6a130ab64d0f",
    "name": "Pluto TV Viaggi",
    "region": "it",
    "category": "Pluto TV",
    "logo": "",
    "streamUrl": "https://jmp2.uk/plu-63c923944207be0007fd0887.m3u8"
  },
  {
    "id": "d4bd824c-d5d1-4940-9c6d-7bad92963ac7",
    "name": "Pluto TV Western",
    "region": "it",
    "category": "Pluto TV",
    "logo": "",
    "streamUrl": "https://jmp2.uk/plu-62e7fb67478a5b0007e6c50c.m3u8"
  },
  {
    "id": "346d91b4-3ef5-483e-855e-a5c70ab52817",
    "name": "Relic Hunter",
    "region": "it",
    "category": "Pluto TV",
    "logo": "",
    "streamUrl": "https://jmp2.uk/plu-67d9836ba1609bdb523f0c9d.m3u8"
  },
  {
    "id": "b87067af-63cb-4680-a273-acee158cb06b",
    "name": "Renegade",
    "region": "it",
    "category": "Pluto TV",
    "logo": "",
    "streamUrl": "https://jmp2.uk/plu-634926e4b51d2d00077819a2.m3u8"
  },
  {
    "id": "05a26c32-3b87-4334-83e7-916bf7088bad",
    "name": "Sanctuary",
    "region": "it",
    "category": "Pluto TV",
    "logo": "",
    "streamUrl": "https://jmp2.uk/plu-63eb57d6c111bc0008fe2658.m3u8"
  },
  {
    "id": "a9225416-510e-4b7d-8472-ae0fa62c8b6d",
    "name": "Settimo Cielo",
    "region": "it",
    "category": "Pluto TV",
    "logo": "",
    "streamUrl": "https://jmp2.uk/plu-6245d3792792150007e20634.m3u8"
  },
  {
    "id": "91118462-15bf-48de-859d-43c227905755",
    "name": "South Park",
    "region": "it",
    "category": "Pluto TV",
    "logo": "",
    "streamUrl": "https://jmp2.uk/plu-62bc1f502b70e3000706298e.m3u8"
  },
  {
    "id": "b545847a-e0d7-450b-bbd1-6bd2c07b29e8",
    "name": "Squadra Speciale Cobra 11",
    "region": "it",
    "category": "Pluto TV",
    "logo": "",
    "streamUrl": "https://jmp2.uk/plu-625e6cc905e09f00073addee.m3u8"
  },
  {
    "id": "b0241f1b-fe27-41df-9157-9be88919ea29",
    "name": "Star Trek: The Original Series",
    "region": "it",
    "category": "Pluto TV",
    "logo": "",
    "streamUrl": "https://jmp2.uk/plu-6581a09edfed030008e12b39.m3u8"
  },
  {
    "id": "06d0e978-6035-41cf-855c-f0b1134fcfae",
    "name": "Star Trek: Voyager",
    "region": "it",
    "category": "Pluto TV",
    "logo": "",
    "streamUrl": "https://jmp2.uk/plu-65cb73d33ba51e00084cabad.m3u8"
  },
  {
    "id": "StorieCriminali.es@IT",
    "name": "Storie Criminali",
    "region": "it",
    "category": "Pluto TV",
    "logo": "",
    "streamUrl": "https://jmp2.uk/plu-66177d18c8311c0008d077d0.m3u8"
  },
  {
    "id": "ffdc33af-9fb1-4cb2-906d-8e0538013a9e",
    "name": "Sulle tracce del crimine",
    "region": "it",
    "category": "Pluto TV",
    "logo": "",
    "streamUrl": "https://jmp2.uk/plu-66d9a98961dbf00008efb5fc.m3u8"
  },
  {
    "id": "e0d19ae0-8459-4522-935a-8ba8dfdd6fa6",
    "name": "Super! Big Time Rush",
    "region": "it",
    "category": "Pluto TV",
    "logo": "",
    "streamUrl": "https://jmp2.uk/plu-666174c9f999220008769012.m3u8"
  },
  {
    "id": "afdcb1ca-632b-4496-94b3-18288a74c078",
    "name": "Super! Cartoni Animati (720p)",
    "region": "it",
    "category": "Pluto TV",
    "logo": "",
    "streamUrl": "https://jmp2.uk/plu-6093f6f8351eb0000754afb8.m3u8"
  },
  {
    "id": "640c285d-595a-4c08-b4ad-7ff43c3fa78b",
    "name": "Super! iCarly",
    "region": "it",
    "category": "Pluto TV",
    "logo": "",
    "streamUrl": "https://jmp2.uk/plu-609401db8cf51c00084b592e.m3u8"
  },
  {
    "id": "4df38267-c0c1-4560-9263-7cd680983e5f",
    "name": "Super! Kids Classics (720p)",
    "region": "it",
    "category": "Pluto TV",
    "logo": "",
    "streamUrl": "https://jmp2.uk/plu-67f4f99729b03f18cb36647e.m3u8"
  },
  {
    "id": "7f565085-1f86-481c-9620-d30d5166a993",
    "name": "Super! Pop",
    "region": "it",
    "category": "Pluto TV",
    "logo": "",
    "streamUrl": "https://jmp2.uk/plu-6093f7b5bb49b90007cecaad.m3u8"
  },
  {
    "id": "555b0932-69ad-4ba9-a229-a28bbc3dc409",
    "name": "Super! SpongeBob (720p)",
    "region": "it",
    "category": "Pluto TV",
    "logo": "",
    "streamUrl": "https://jmp2.uk/plu-6093f9281db477000759fce0.m3u8"
  },
  {
    "id": "613d9306-18af-4c4c-be4a-c148d596f86a",
    "name": "Super! Victorious",
    "region": "it",
    "category": "Pluto TV",
    "logo": "",
    "streamUrl": "https://jmp2.uk/plu-63c012504faf1c0007abfa93.m3u8"
  },
  {
    "id": "017b2a73-8dde-4907-bcb9-61e2d4fad42d",
    "name": "Super! Zoey 101",
    "region": "it",
    "category": "Pluto TV",
    "logo": "",
    "streamUrl": "https://jmp2.uk/plu-6304ed62410a4c00083c0291.m3u8"
  },
  {
    "id": "ae547e31-6e7e-4722-8923-35ed64496e85",
    "name": "Tandem",
    "region": "it",
    "category": "Pluto TV",
    "logo": "",
    "streamUrl": "https://jmp2.uk/plu-66a8c8b3d2d50d000821fc4c.m3u8"
  },
  {
    "id": "40cf0228-e840-46df-a0db-8a25cb2bc6dd",
    "name": "Teen Mom",
    "region": "it",
    "category": "Pluto TV",
    "logo": "",
    "streamUrl": "https://jmp2.uk/plu-62e7fc8c0d061100083946a9.m3u8"
  },
  {
    "id": "3053e651-60f2-424e-9a6d-b9b2f81c3066",
    "name": "Teenage Mutant Ninja Turtles (720p)",
    "region": "it",
    "category": "Pluto TV",
    "logo": "",
    "streamUrl": "https://jmp2.uk/plu-62619405c733e8000732d1fe.m3u8"
  },
  {
    "id": "d89b11bf-ca9a-49a9-9e75-fc075bc4074e",
    "name": "The Asylum",
    "region": "it",
    "category": "Pluto TV",
    "logo": "",
    "streamUrl": "https://jmp2.uk/plu-62e8d5369e48940007fc1dc1.m3u8"
  },
  {
    "id": "cf52c04a-8e32-441c-ba61-288745938ca4",
    "name": "Top Gear",
    "region": "it",
    "category": "Pluto TV",
    "logo": "",
    "streamUrl": "https://jmp2.uk/plu-64c109a4798def0008a6e03e.m3u8"
  },
  {
    "id": "0e8a7270-8d1f-4f30-9b5c-2f68abafc0f8",
    "name": "Triton Poker (720p)",
    "region": "it",
    "category": "Pluto TV",
    "logo": "",
    "streamUrl": "https://jmp2.uk/plu-6616a51124e1d00008761a7e.m3u8"
  },
  {
    "id": "af2180aa-871b-4a3f-be3c-8af5b18292fd",
    "name": "UFC",
    "region": "it",
    "category": "Pluto TV",
    "logo": "",
    "streamUrl": "https://jmp2.uk/plu-679203d4bc03978b9b4b79a6.m3u8"
  },
  {
    "id": "108a1f76-e724-492d-b80f-d776e14b3b31",
    "name": "Wicked Tuna",
    "region": "it",
    "category": "Pluto TV",
    "logo": "",
    "streamUrl": "https://jmp2.uk/plu-67c832cc9b53325ee16fb899.m3u8"
  },
  {
    "id": "d316b953-aef5-44ab-9944-b20bcd54fd1c",
    "name": "Winx Club",
    "region": "it",
    "category": "Pluto TV",
    "logo": "",
    "streamUrl": "https://jmp2.uk/plu-67851bd7d648bf0008c00bc2.m3u8"
  },
  {
    "id": "86cedc7b-a55e-4ce8-955f-d87f3f20e6c7",
    "name": "World Poker Tour",
    "region": "it",
    "category": "Pluto TV",
    "logo": "",
    "streamUrl": "https://jmp2.uk/plu-608016e446d73500075ea7e0.m3u8"
  },
  {
    "id": "ca0f212e-e8c8-4fe3-946f-8abf1a002a1d",
    "name": "Yu-Gi-Oh!",
    "region": "it",
    "category": "Pluto TV",
    "logo": "",
    "streamUrl": "https://jmp2.uk/plu-63eb82e24e83e70008ab735f.m3u8"
  }
]